torchsummaryDynamic
